{"assets":{"5BA6DF7ACEF516F7DAB78587CF30CE20":{"type":"texture","index":1,"assetRequest":{"type":"slide","state":"contents","slide":"none"},"url":{"native":"assets\/54408F90-20E0-4F11-AC33-B78A64933D35.pdf"},"width":1920,"height":1080},"B2F58D9C1B4F61216220457433BA22A1":{"type":"texture","index":0,"assetRequest":{"type":"slide","state":"contents","slide":"none"},"url":{"native":"assets\/54408F90-20E0-4F11-AC33-B78A64933D35.pdf"},"width":1920,"height":1080}},"events":[{"effects":[{"beginTime":0,"baseLayer":{"animations":[],"initialState":{"affineTransform":[1,0,0,1,0,0],"masksToBounds":false,"rotation":0,"scale":1,"position":{"pointX":960,"pointY":540},"width":1920,"sublayerTransform":[1,0,0,0,0,1,0,0,0,0,1,0,0,0,0,1],"contentsRect":{"y":0,"x":0,"width":1,"height":1},"opacity":1,"edgeAntialiasingMask":251658240,"height":1080,"hidden":false,"anchorPoint":{"pointX":0.5,"pointY":0.5}},"objectID":"0","layers":[{"animations":[],"initialState":{"affineTransform":[1,0,0,1,0,0],"masksToBounds":false,"rotation":0,"scale":1,"position":{"pointX":960,"pointY":540},"width":1920,"sublayerTransform":[1,0,0,0,0,1,0,0,0,0,1,-0.00035007912466775983,0,0,0,1],"contentsRect":{"y":0,"x":0,"width":1,"height":1},"opacity":1,"edgeAntialiasingMask":251658240,"height":1080,"hidden":false,"anchorPoint":{"pointX":0.5,"pointY":0.5}},"layers":[{"animations":[],"layers":[],"texturedRectangle":{"isBackgroundTexture":false,"singleTextureOpacity":1,"textureType":0,"textBaseline":0,"textXHeight":0,"isVerticalText":false},"initialState":{"affineTransform":[1,0,0,1,0,0],"masksToBounds":false,"rotation":0,"scale":1,"position":{"pointX":960,"pointY":540},"width":1920,"sublayerTransform":[1,0,0,0,0,1,0,0,0,0,1,0,0,0,0,1],"contentsRect":{"y":0,"x":0,"width":1,"height":1},"opacity":1,"edgeAntialiasingMask":0,"height":1080,"hidden":false,"anchorPoint":{"pointX":0.5,"pointY":0.5}},"texture":"5BA6DF7ACEF516F7DAB78587CF30CE20"},{"animations":[{"additive":false,"timeOffset":0,"beginTime":0,"from":{"scalar":false},"repeatCount":0,"fillMode":"both","duration":0.01,"autoreverses":false,"property":"hidden","to":{"scalar":true},"removedOnCompletion":false}],"layers":[],"texturedRectangle":{"isBackgroundTexture":false,"singleTextureOpacity":1,"textureType":0,"textBaseline":0,"textXHeight":0,"isVerticalText":false},"initialState":{"affineTransform":[1,0,0,1,0,0],"masksToBounds":false,"rotation":0,"scale":1,"position":{"pointX":960,"pointY":540},"width":1920,"sublayerTransform":[1,0,0,0,0,1,0,0,0,0,1,0,0,0,0,1],"contentsRect":{"y":0,"x":0,"width":1,"height":1},"opacity":1,"edgeAntialiasingMask":0,"height":1080,"hidden":false,"anchorPoint":{"pointX":0.5,"pointY":0.5}},"texture":"B2F58D9C1B4F61216220457433BA22A1"}]}]},"effects":[],"duration":0.01,"type":"transition","attributes":{"direction":0},"name":"none","objectID":"0"}],"automaticPlay":false,"hyperlinks":[],"accessibility":[{"text":"linkedin_pic.jpeg","targetRectangle":{"y":258.74386596679688,"x":460.29776000976562,"width":251.66873168945312,"height":251.66873168945312}},{"text":"Beta testers","targetRectangle":{"y":579.03736591339111,"x":1150.4905566406251,"width":173.90999999999985,"height":36.129791259765625}},{"text":"Jocelyne Vreede (& students)","targetRectangle":{"y":652.03736591339111,"x":1043.5105566406251,"width":387.86999999999989,"height":35.160003662109375}},{"text":"Christoph Dellago (& students\/postdocs, especially Gyorgy Hantal)","targetRectangle":{"y":688.03736591339111,"x":996.47055664062509,"width":481.94999999999982,"height":71.160003662109375}},{"text":"...and all the many people who post OPS questions on either GitHub or MatterModeling.StackExchange!","targetRectangle":{"y":832.03736591339111,"x":998.21055664062499,"width":486.80999999999983,"height":107.16000366210938}},{"text":"PIs who supported OpenPathSampling development","targetRectangle":{"y":285.13673400878906,"x":863.88554954528809,"width":747.12000000000012,"height":36.129791259765625}},{"text":"Peter Bolhuis (UvA)","targetRectangle":{"y":358.13673400878906,"x":1108.0105495452881,"width":258.87000000000012,"height":35.160003662109375}},{"text":"John Chodera (MSKCC)","targetRectangle":{"y":394.13673400878906,"x":1076.0305495452881,"width":322.83000000000015,"height":35.160003662109375}},{"text":"Frank Noé (FU Berlin)","targetRectangle":{"y":430.13673400878906,"x":1094.1205495452882,"width":286.64999999999986,"height":35.160003662109375}},{"text":"Ralf Everaers (ENS Lyon)","targetRectangle":{"y":466.13673400878906,"x":1070.7955495452882,"width":333.29999999999995,"height":35.160003662109375}},{"text":"Acknowledgments","targetRectangle":{"y":47.75,"x":612.24000000000001,"width":695.51999999999998,"height":101}},{"text":"Funding support from E-CAM, a European Union Horizon 2020 Centre of Excellence","targetRectangle":{"y":987.99345368146896,"x":390.11750488281245,"width":1191.1500000000001,"height":36.129791259765625}},{"text":"Major contributors (>1000 lines)","targetRectangle":{"y":672.0094199180603,"x":359.64714336395264,"width":452.97000000000003,"height":36.129791259765625}},{"text":"Jan-Hendrik Prinz","targetRectangle":{"y":745.0094199180603,"x":466.13214336395265,"width":240,"height":35.160003662109375}},{"text":"Sander Roet","targetRectangle":{"y":781.0094199180603,"x":502.23714336395267,"width":167.78999999999996,"height":35.160003662109375}},{"text":"Hendrik Jung","targetRectangle":{"y":817.0094199180603,"x":496.65714336395263,"width":178.95000000000005,"height":35.160003662109375}},{"text":"Andreas Singraber","targetRectangle":{"y":853.0094199180603,"x":461.67714336395267,"width":248.91000000000003,"height":35.160003662109375}},{"text":"Alberto Pérez de Alba Ortíz","targetRectangle":{"y":889.0094199180603,"x":404.76714336395264,"width":362.73000000000002,"height":35.160003662109375}},{"text":"Sander Roet","targetRectangle":{"y":535.055588722229,"x":497.22713268280029,"width":177.81000000000006,"height":36.129791259765625}},{"text":"(OpenPathSampling Maintainer)","targetRectangle":{"y":572.055588722229,"x":358.97213268280029,"width":454.31999999999994,"height":36.129791259765625}}],"baseLayer":{"animations":[],"initialState":{"affineTransform":[1,0,0,1,0,0],"masksToBounds":false,"rotation":0,"scale":1,"position":{"pointX":960,"pointY":540},"width":1920,"sublayerTransform":[1,0,0,0,0,1,0,0,0,0,1,0,0,0,0,1],"contentsRect":{"y":0,"x":0,"width":1,"height":1},"opacity":1,"edgeAntialiasingMask":251658240,"height":1080,"hidden":false,"anchorPoint":{"pointX":0.5,"pointY":0.5}},"objectID":"0","layers":[{"animations":[],"initialState":{"affineTransform":[1,0,0,1,0,0],"masksToBounds":false,"rotation":0,"scale":1,"position":{"pointX":960,"pointY":540},"width":1920,"sublayerTransform":[1,0,0,0,0,1,0,0,0,0,1,-0.00035007912466775983,0,0,0,1],"contentsRect":{"y":0,"x":0,"width":1,"height":1},"opacity":1,"edgeAntialiasingMask":251658240,"height":1080,"hidden":false,"anchorPoint":{"pointX":0.5,"pointY":0.5}},"layers":[{"animations":[],"layers":[],"texturedRectangle":{"isBackgroundTexture":false,"singleTextureOpacity":1,"textureType":0,"textBaseline":0,"textXHeight":0,"isVerticalText":false},"initialState":{"affineTransform":[1,0,0,1,0,0],"masksToBounds":false,"rotation":0,"scale":1,"position":{"pointX":960,"pointY":540},"width":1920,"sublayerTransform":[1,0,0,0,0,1,0,0,0,0,1,0,0,0,0,1],"contentsRect":{"y":0,"x":0,"width":1,"height":1},"opacity":1,"edgeAntialiasingMask":0,"height":1080,"hidden":false,"anchorPoint":{"pointX":0.5,"pointY":0.5}},"texture":"B2F58D9C1B4F61216220457433BA22A1"}]}]}}]}